configular/__init__.py
configular/base_loader.py
configular/base_secret_manager.py
configular/constance_loader.py
configular/credstash_manager.py
configular/decorators.py
configular/django_loader.py
configular/environ_loader.py
configular/exceptions.py
configular-1.1.0.dist-info/LICENSE
configular-1.1.0.dist-info/METADATA
configular-1.1.0.dist-info/WHEEL
configular-1.1.0.dist-info/top_level.txt
configular-1.1.0.dist-info/RECORD
