Metadata-Version: 2.1
Name: configular
Version: 1.1.0
Summary: Support hierarchical loading of applications settings from a number of sources.
Author: Aaron McMillin
Author-email: amcmillin@jbssolutions.com
Classifier: Development Status :: 5 - Production/Stable
Classifier: Intended Audience :: Developers
Classifier: Topic :: Software Development :: Libraries :: Python Modules
Classifier: Topic :: System :: Installation/Setup
Classifier: Framework :: Django
Classifier: License :: OSI Approved :: ISC License (ISCL)
Classifier: Programming Language :: Python :: 3
Classifier: Programming Language :: Python :: 3.8
Classifier: Programming Language :: Python :: 3.9
Classifier: Programming Language :: Python :: 3.10
Classifier: Programming Language :: Python :: 3 :: Only
License-File: LICENSE
Provides-Extra: constance
Requires-Dist: django-constance (<3,>=2.0.0) ; extra == 'constance'
Provides-Extra: credstash
Requires-Dist: credstash (<2,>=1.0.0) ; extra == 'credstash'
Provides-Extra: django
Requires-Dist: Django (<4,>=2.2) ; extra == 'django'
Provides-Extra: test
Requires-Dist: django-constance ; extra == 'test'
Requires-Dist: redis ; extra == 'test'
Requires-Dist: pytest ; extra == 'test'
Requires-Dist: pytest-coverage ; extra == 'test'
Requires-Dist: pytest-django ; extra == 'test'
Requires-Dist: pytest-mock ; extra == 'test'
Requires-Dist: credstash (<2,>=1.0.0) ; extra == 'test'
Requires-Dist: Django (<5,>=2.2) ; extra == 'test'
